MANIFEST.in
README
__init__.py
__pkginfo__.py
authplugin.py
entities.py
hooks.py
schema.py
setup.py
views.py
cubicweb_oauth.egg-info/PKG-INFO
cubicweb_oauth.egg-info/SOURCES.txt
cubicweb_oauth.egg-info/dependency_links.txt
cubicweb_oauth.egg-info/not-zip-safe
cubicweb_oauth.egg-info/requires.txt
cubicweb_oauth.egg-info/top_level.txt
i18n/en.po
i18n/es.po
i18n/fr.po
migration/0.2.0_Any.py
migration/postcreate.py
migration/precreate.py
test/pytestconf.py
test/test_oauth.py