Metadata-Version: 1.1
Name: cubicweb-oauth
Version: 0.2.0
Summary: External service (Facebook, Twitter, Google+, etc) Authentication
Home-page: http://www.cubicweb.org/project/cubicweb-oauth
Author: LOGILAB S.A. (Paris, FRANCE)
Author-email: contact@logilab.fr
License: LGPL
Platform: UNKNOWN
Classifier: Environment :: Web Environment
Classifier: Framework :: CubicWeb
Classifier: Programming Language :: Python
Classifier: Programming Language :: JavaScript
